utrcalling/__init__.py
utrcalling/_metadata.py
utrcalling/core/__init__.py
utrcalling/core/anndata_processing.py
utrcalling/core/core.py
utrcalling/core/helpers.py
utrcalling/core/module_log.py
utrcalling/core/peak_calling.py
utrcalling/core/peak_calling_anndata.py
utrcalling/core/protocols.py
utrcalling/core/utr_mapping.py
utrcalling/core/utr_reference.py
utrcalling/tests/__init__.py
utrcalling/tests/test_anndata_processing.py
utrcalling/tests/test_case.py
utrcalling/tests/test_compute_mean_utr_sizes.py
utrcalling/tests/test_core.py
utrcalling/tests/test_package_details.py
utrcalling/tests/test_peak_calling.py
utrcalling/tests/test_protocols.py
utrcalling/tests/test_utr_mapping.py
utrcalling/tests/test_utr_reference.py
utrcalling/tests/test_data/anndata_test.h5ad
utrcalling/tests/test_data/capseq_test_sorted.bam
utrcalling/tests/test_data/capseq_test_sorted.bam.bai
utrcalling/tests/test_data/generate_test_bam_capseq.py
utrcalling/tests/test_data/generate_test_bam_data.py
utrcalling/tests/test_data/generate_test_bam_smartseq3.py
utrcalling/tests/test_data/smartseq3_anno.csv
utrcalling/tests/test_data/smartseq3_test_sorted.bam
utrcalling/tests/test_data/smartseq3_test_sorted.bam.bai
utrcalling/tests/test_data/synthetic_data.py
utrcalling/tests/test_data/test_CapPhospho_genome_102_coordsort.bam
utrcalling/tests/test_data/test_CapPhospho_genome_102_coordsort.bam.bai
utrcalling/tests/test_data/test_UTR_reference.pkl
utrcalling/tests/test_data/test_UTR_reference_5prime.pkl
utrcalling/tests/test_data/test_UTRoldNSCgenome_bwt2_102_sort.bam
utrcalling/tests/test_data/test_UTRoldNSCgenome_bwt2_102_sort.bam.bai
utrcalling/tests/test_data/test_UTRoldNSCgenome_bwt2_102_sort_OLD.bam
utrcalling/tests/test_data/test_UTRoldNSCgenome_bwt2_102_sort_OLD.bam.bai
utrcalling/tests/test_data/test_UTRoldNSCgenome_bwt2_102_sort_dup_umi.bam
utrcalling/tests/test_data/test_UTRyoungNSCgenome_bwt2_102_sort.bam
utrcalling/tests/test_data/test_UTRyoungNSCgenome_bwt2_102_sort.bam.bai
utrcalling-1.2.5.dist-info/METADATA
utrcalling-1.2.5.dist-info/WHEEL
utrcalling-1.2.5.dist-info/entry_points.txt
utrcalling-1.2.5.dist-info/top_level.txt
utrcalling-1.2.5.dist-info/RECORD
