Metadata-Version: 2.1
Name: utrcalling
Version: 1.2.5
Summary: Package with tools to calculate molecule UTR sizes from RNA sequencing reads.
Home-page: https://github.com/AndreMacedo88/utrcalling
Author: André Lopes Martins Macedo
Author-email: andre.lopes.macedo@gmail.com
Classifier: Development Status :: 3 - Alpha
Classifier: Intended Audience :: Science/Research
Classifier: Programming Language :: Python :: 3.9
Classifier: License :: OSI Approved :: BSD License
Classifier: Operating System :: OS Independent
Requires-Dist: numpy (>=1.22.3)
Requires-Dist: pandas (>=1.3.0)
Requires-Dist: scipy
Requires-Dist: scikit-learn
Requires-Dist: regex
Requires-Dist: rapidfuzz (>=2.0.0)
Requires-Dist: joblib
Requires-Dist: anndata
Requires-Dist: scanpy
Requires-Dist: gtfparse (<2,>=1.2.1)
Requires-Dist: htseq
Requires-Dist: pybedtools
Requires-Dist: tqdm
Requires-Dist: psutil
Requires-Dist: pympler
Requires-Dist: coloredlogs
Requires-Dist: verboselogs
Requires-Dist: colorama
